<?xml version="1.0" encoding="UTF-8" standalone="no"?><xml><dados><deputado_><id>2436</id><uri>https://dadosabertos.camara.leg.br/api/v2/deputados/2436</uri><nome>AFONSO BARATA</nome><siglaPartido/><uriPartido/><siglaUf>RN</siglaUf><idLegislatura>30</idLegislatura><urlFoto>http://www.camara.leg.br/internet/deputado/bandep/2436.jpg</urlFoto><dados_deputado/></deputado_><deputado_><id>4155</id><uri>https://dadosabertos.camara.leg.br/api/v2/deputados/4155</uri><nome>AGAPITO PEREIRA</nome><siglaPartido/><uriPartido/><siglaUf>AM</siglaUf><idLegislatura>30</idLegislatura><urlFoto>http://www.camara.leg.br/internet/deputado/bandep/4155.jpg</urlFoto><dados_deputado/></deputado_><deputado_><id>4445</id><uri>https://dadosabertos.camara.leg.br/api/v2/deputados/4445</uri><nome>AGRIPINO AZEVEDO</nome><siglaPartido/><uriPartido/><siglaUf>MA</siglaUf><idLegislatura>30</idLegislatura><urlFoto>http://www.camara.leg.br/internet/deputado/bandep/4445.jpg</urlFoto><dados_deputado><cpf/><nomeCivil>Agrippino Azevedo</nomeCivil><sexo>M</sexo><urlWebsite/><redeSocial/><dataNascimento>1864-03-16</dataNascimento><dataFalecimento/><ufNascimento>MA</ufNascimento><municipioNascimento>São Luís</municipioNascimento><escolaridade>Superior</escolaridade></dados_deputado></deputado_><deputado_><id>2449</id><uri>https://dadosabertos.camara.leg.br/api/v2/deputados/2449</uri><nome>AGUIAR DE MELO</nome><siglaPartido/><uriPartido/><siglaUf>SE</siglaUf><idLegislatura>30</idLegislatura><urlFoto>http://www.camara.leg.br/internet/deputado/bandep/2449.jpg</urlFoto><dados_deputado/></deputado_><deputado_><id>2342</id><uri>https://dadosabertos.camara.leg.br/api/v2/deputados/2342</uri><nome>AIRES DA SILVA</nome><siglaPartido/><uriPartido/><siglaUf>GO</siglaUf><idLegislatura>30</idLegislatura><urlFoto>http://www.camara.leg.br/internet/deputado/bandep/2342.jpg</urlFoto><dados_deputado/></deputado_><deputado_><id>4446</id><uri>https://dadosabertos.camara.leg.br/api/v2/deputados/4446</uri><nome>ALAOR PRATA</nome><siglaPartido/><uriPartido/><siglaUf>MG</siglaUf><idLegislatura>30</idLegislatura><urlFoto>http://www.camara.leg.br/internet/deputado/bandep/4446.jpg</urlFoto><dados_deputado/></deputado_><deputado_><id>4105</id><uri>https://dadosabertos.camara.leg.br/api/v2/deputados/4105</uri><nome>ALBERTO DE ABREU</nome><siglaPartido/><uriPartido/><siglaUf>PR</siglaUf><idLegislatura>30</idLegislatura><urlFoto>http://www.camara.leg.br/internet/deputado/bandep/4105.jpg</urlFoto><dados_deputado/></deputado_><deputado_><id>2159</id><uri>https://dadosabertos.camara.leg.br/api/v2/deputados/2159</uri><nome>ALBERTO MARANHÃO</nome><siglaPartido/><uriPartido/><siglaUf>RN</siglaUf><idLegislatura>30</idLegislatura><urlFoto>http://www.camara.leg.br/internet/deputado/bandep/2159.jpg</urlFoto><dados_deputado/></deputado_><deputado_><id>4305</id><uri>https://dadosabertos.camara.leg.br/api/v2/deputados/4305</uri><nome>ALBERTO SARMENTO</nome><siglaPartido/><uriPartido/><siglaUf>SP</siglaUf><idLegislatura>30</idLegislatura><urlFoto>http://www.camara.leg.br/internet/deputado/bandep/4305.jpg</urlFoto><dados_deputado/></deputado_><deputado_><id>4166</id><uri>https://dadosabertos.camara.leg.br/api/v2/deputados/4166</uri><nome>ALFREDO DE MAIA</nome><siglaPartido/><uriPartido/><siglaUf>AL</siglaUf><idLegislatura>30</idLegislatura><urlFoto>http://www.camara.leg.br/internet/deputado/bandep/4166.jpg</urlFoto><dados_deputado><cpf/><nomeCivil>Alfredo de Maya</nomeCivil><sexo>M</sexo><urlWebsite/><redeSocial/><dataNascimento>1880-02-07</dataNascimento><dataFalecimento/><ufNascimento>AL</ufNascimento><municipioNascimento>Atalaia</municipioNascimento><escolaridade>Superior</escolaridade></dados_deputado></deputado_><deputado_><id>2260</id><uri>https://dadosabertos.camara.leg.br/api/v2/deputados/2260</uri><nome>ALFREDO RUI</nome><siglaPartido/><uriPartido/><siglaUf>BA</siglaUf><idLegislatura>30</idLegislatura><urlFoto>http://www.camara.leg.br/internet/deputado/bandep/2260.jpg</urlFoto><dados_deputado/></deputado_><deputado_><id>4143</id><uri>https://dadosabertos.camara.leg.br/api/v2/deputados/4143</uri><nome>ALMEIDA FAGUNDES</nome><siglaPartido/><uriPartido/><siglaUf>RJ</siglaUf><idLegislatura>30</idLegislatura><urlFoto>http://www.camara.leg.br/internet/deputado/bandep/4143.jpg</urlFoto><dados_deputado/></deputado_><deputado_><id>2437</id><uri>https://dadosabertos.camara.leg.br/api/v2/deputados/2437</uri><nome>ÁLVARO BATISTA</nome><siglaPartido/><uriPartido/><siglaUf>RS</siglaUf><idLegislatura>30</idLegislatura><urlFoto>http://www.camara.leg.br/internet/deputado/bandep/2437.jpg</urlFoto><dados_deputado/></deputado_><deputado_><id>4107</id><uri>https://dadosabertos.camara.leg.br/api/v2/deputados/4107</uri><nome>ÁLVARO BOTELHO</nome><siglaPartido/><uriPartido/><siglaUf>MG</siglaUf><idLegislatura>30</idLegislatura><urlFoto>http://www.camara.leg.br/internet/deputado/bandep/4107.jpg</urlFoto><dados_deputado><cpf/><nomeCivil>Álvaro Augusto de Andrade Botelho</nomeCivil><sexo>M</sexo><urlWebsite/><redeSocial/><dataNascimento>1860-02-08</dataNascimento><dataFalecimento/><ufNascimento>MG</ufNascimento><municipioNascimento>Lavras</municipioNascimento><escolaridade>Superior</escolaridade></dados_deputado></deputado_><deputado_><id>2250</id><uri>https://dadosabertos.camara.leg.br/api/v2/deputados/2250</uri><nome>ÁLVARO CARVALHO</nome><siglaPartido/><uriPartido/><siglaUf>SP</siglaUf><idLegislatura>30</idLegislatura><urlFoto>http://www.camara.leg.br/internet/deputado/bandep/2250.jpg</urlFoto><dados_deputado><cpf/><nomeCivil>Alvaro Augusto da Costa Carvalho</nomeCivil><sexo>M</sexo><urlWebsite/><redeSocial/><dataNascimento>1865-09-23</dataNascimento><dataFalecimento/><ufNascimento>SP</ufNascimento><municipioNascimento>Piracicaba</municipioNascimento><escolaridade/></dados_deputado></deputado_><deputado_><id>2398</id><uri>https://dadosabertos.camara.leg.br/api/v2/deputados/2398</uri><nome>ÁLVARO FERNANDES</nome><siglaPartido/><uriPartido/><siglaUf>CE</siglaUf><idLegislatura>30</idLegislatura><urlFoto>http://www.camara.leg.br/internet/deputado/bandep/2398.jpg</urlFoto><dados_deputado/></deputado_><deputado_><id>130153</id><uri>https://dadosabertos.camara.leg.br/api/v2/deputados/130153</uri><nome>ANÍBAL TOLEDO</nome><siglaPartido/><uriPartido/><siglaUf>MT</siglaUf><idLegislatura>30</idLegislatura><urlFoto>http://www.camara.leg.br/internet/deputado/bandep/130153.jpg</urlFoto><dados_deputado/></deputado_><deputado_><id>1971</id><uri>https://dadosabertos.camara.leg.br/api/v2/deputados/1971</uri><nome>ANTERO BOTELHO</nome><siglaPartido/><uriPartido/><siglaUf>MG</siglaUf><idLegislatura>30</idLegislatura><urlFoto>http://www.camara.leg.br/internet/deputado/bandep/1971.jpg</urlFoto><dados_deputado><cpf/><nomeCivil>Antero de Andrade Botelho</nomeCivil><sexo>M</sexo><urlWebsite/><redeSocial/><dataNascimento>1873-04-22</dataNascimento><dataFalecimento/><ufNascimento>MG</ufNascimento><municipioNascimento>Lavras</municipioNascimento><escolaridade>Superior</escolaridade></dados_deputado></deputado_><deputado_><id>2370</id><uri>https://dadosabertos.camara.leg.br/api/v2/deputados/2370</uri><nome>ANTONINO FREIRE</nome><siglaPartido/><uriPartido/><siglaUf>PI</siglaUf><idLegislatura>30</idLegislatura><urlFoto>http://www.camara.leg.br/internet/deputado/bandep/2370.jpg</urlFoto><dados_deputado><cpf/><nomeCivil>Antonino Freire da Silva</nomeCivil><sexo>M</sexo><urlWebsite/><redeSocial/><dataNascimento>1878-05-10</dataNascimento><dataFalecimento/><ufNascimento>PI</ufNascimento><municipioNascimento>Amarante</municipioNascimento><escolaridade>Superior</escolaridade></dados_deputado></deputado_><deputado_><id>2261</id><uri>https://dadosabertos.camara.leg.br/api/v2/deputados/2261</uri><nome>ANTONIO CALMON</nome><siglaPartido/><uriPartido/><siglaUf>BA</siglaUf><idLegislatura>30</idLegislatura><urlFoto>http://www.camara.leg.br/internet/deputado/bandep/2261.jpg</urlFoto><dados_deputado/></deputado_><deputado_><id>4671</id><uri>https://dadosabertos.camara.leg.br/api/v2/deputados/4671</uri><nome>ANTONIO CARLOS</nome><siglaPartido>PRM</siglaPartido><uriPartido>https://dadosabertos.camara.leg.br/api/v2/partidos/36821</uriPartido><siglaUf>MG</siglaUf><idLegislatura>30</idLegislatura><urlFoto>http://www.camara.leg.br/internet/deputado/bandep/4671.jpg</urlFoto><dados_deputado><cpf/><nomeCivil>Antonio Carlos Ribeiro de Andrada</nomeCivil><sexo>M</sexo><urlWebsite/><redeSocial/><dataNascimento>1870-09-05</dataNascimento><dataFalecimento/><ufNascimento>MG</ufNascimento><municipioNascimento>Barbacena</municipioNascimento><escolaridade>Superior</escolaridade></dados_deputado></deputado_><deputado_><id>2413</id><uri>https://dadosabertos.camara.leg.br/api/v2/deputados/2413</uri><nome>ANTONIO MARTINS</nome><siglaPartido/><uriPartido/><siglaUf>MG</siglaUf><idLegislatura>30</idLegislatura><urlFoto>http://www.camara.leg.br/internet/deputado/bandep/2413.jpg</urlFoto><dados_deputado/></deputado_><deputado_><id>2320</id><uri>https://dadosabertos.camara.leg.br/api/v2/deputados/2320</uri><nome>ANTONIO MUNIZ</nome><siglaPartido/><uriPartido/><siglaUf>BA</siglaUf><idLegislatura>30</idLegislatura><urlFoto>http://www.camara.leg.br/internet/deputado/bandep/2320.jpg</urlFoto><dados_deputado/></deputado_><deputado_><id>2191</id><uri>https://dadosabertos.camara.leg.br/api/v2/deputados/2191</uri><nome>ANTONIO NOGUEIRA</nome><siglaPartido/><uriPartido/><siglaUf>AM</siglaUf><idLegislatura>30</idLegislatura><urlFoto>http://www.camara.leg.br/internet/deputado/bandep/2191.jpg</urlFoto><dados_deputado/></deputado_><deputado_><id>2450</id><uri>https://dadosabertos.camara.leg.br/api/v2/deputados/2450</uri><nome>ANTONIO ROLLEMBERG</nome><siglaPartido/><uriPartido/><siglaUf>SE</siglaUf><idLegislatura>30</idLegislatura><urlFoto>http://www.camara.leg.br/internet/deputado/bandep/2450.jpg</urlFoto><dados_deputado/></deputado_><deputado_><id>2438</id><uri>https://dadosabertos.camara.leg.br/api/v2/deputados/2438</uri><nome>ANTUNES MACIEL JÚNIOR</nome><siglaPartido/><uriPartido/><siglaUf>RS</siglaUf><idLegislatura>30</idLegislatura><urlFoto>http://www.camara.leg.br/internet/deputado/bandep/2438.jpg</urlFoto><dados_deputado/></deputado_><deputado_><id>2359</id><uri>https://dadosabertos.camara.leg.br/api/v2/deputados/2359</uri><nome>ARISTARCO LOPES</nome><siglaPartido/><uriPartido/><siglaUf>PE</siglaUf><idLegislatura>30</idLegislatura><urlFoto>http://www.camara.leg.br/internet/deputado/bandep/2359.jpg</urlFoto><dados_deputado/></deputado_><deputado_><id>2404</id><uri>https://dadosabertos.camara.leg.br/api/v2/deputados/2404</uri><nome>ARISTIDES CAIRE</nome><siglaPartido/><uriPartido/><siglaUf>DF</siglaUf><idLegislatura>30</idLegislatura><urlFoto>http://www.camara.leg.br/internet/deputado/bandep/2404.jpg</urlFoto><dados_deputado/></deputado_><deputado_><id>4678</id><uri>https://dadosabertos.camara.leg.br/api/v2/deputados/4678</uri><nome>ARLINDO LEONI</nome><siglaPartido/><uriPartido/><siglaUf>BA</siglaUf><idLegislatura>30</idLegislatura><urlFoto>http://www.camara.leg.br/internet/deputado/bandep/4678.jpg</urlFoto><dados_deputado><cpf/><nomeCivil>Arlindo Batista Leoni</nomeCivil><sexo>M</sexo><urlWebsite/><redeSocial/><dataNascimento>1869-01-29</dataNascimento><dataFalecimento/><ufNascimento>BA</ufNascimento><municipioNascimento>Barra da Estiva</municipioNascimento><escolaridade>Superior</escolaridade></dados_deputado></deputado_><deputado_><id>2179</id><uri>https://dadosabertos.camara.leg.br/api/v2/deputados/2179</uri><nome>ARNOLFO DE AZEVEDO</nome><siglaPartido/><uriPartido/><siglaUf>SP</siglaUf><idLegislatura>30</idLegislatura><urlFoto>http://www.camara.leg.br/internet/deputado/bandep/2179.jpg</urlFoto><dados_deputado/></deputado_><deputado_><id>2280</id><uri>https://dadosabertos.camara.leg.br/api/v2/deputados/2280</uri><nome>ARTUR  COLARES MOREIRA</nome><siglaPartido/><uriPartido/><siglaUf>MA</siglaUf><idLegislatura>30</idLegislatura><urlFoto>http://www.camara.leg.br/internet/deputado/bandep/2280.jpg</urlFoto><dados_deputado/></deputado_><deputado_><id>2285</id><uri>https://dadosabertos.camara.leg.br/api/v2/deputados/2285</uri><nome>ARTUR BERNARDES</nome><siglaPartido>PRM</siglaPartido><uriPartido>https://dadosabertos.camara.leg.br/api/v2/partidos/36821</uriPartido><siglaUf>MG</siglaUf><idLegislatura>30</idLegislatura><urlFoto>http://www.camara.leg.br/internet/deputado/bandep/2285.jpg</urlFoto><dados_deputado><cpf/><nomeCivil>Arthur da Silva Bernardes</nomeCivil><sexo>M</sexo><urlWebsite/><redeSocial/><dataNascimento>1875-08-08</dataNascimento><dataFalecimento/><ufNascimento>MG</ufNascimento><municipioNascimento>Viçosa</municipioNascimento><escolaridade>Superior</escolaridade></dados_deputado></deputado_><deputado_><id>2136</id><uri>https://dadosabertos.camara.leg.br/api/v2/deputados/2136</uri><nome>ASTOLFO DUTRA</nome><siglaPartido/><uriPartido/><siglaUf>MG</siglaUf><idLegislatura>30</idLegislatura><urlFoto>http://www.camara.leg.br/internet/deputado/bandep/2136.jpg</urlFoto><dados_deputado/></deputado_><deputado_><id>130136</id><uri>https://dadosabertos.camara.leg.br/api/v2/deputados/130136</uri><nome>AUGUSTO CARLOS DE SOUZA E SILVA</nome><siglaPartido>PNI</siglaPartido><uriPartido>https://dadosabertos.camara.leg.br/api/v2/partidos/36807</uriPartido><siglaUf>RJ</siglaUf><idLegislatura>30</idLegislatura><urlFoto>http://www.camara.leg.br/internet/deputado/bandep/130136.jpg</urlFoto><dados_deputado/></deputado_><deputado_><id>4147</id><uri>https://dadosabertos.camara.leg.br/api/v2/deputados/4147</uri><nome>AUGUSTO DE FREITAS</nome><siglaPartido/><uriPartido/><siglaUf>BA</siglaUf><idLegislatura>30</idLegislatura><urlFoto>http://www.camara.leg.br/internet/deputado/bandep/4147.jpg</urlFoto><dados_deputado><cpf/><nomeCivil>José Augusto de Freitas</nomeCivil><sexo>M</sexo><urlWebsite/><redeSocial/><dataNascimento>1857-11-17</dataNascimento><dataFalecimento/><ufNascimento>BA</ufNascimento><municipioNascimento>Salvador</municipioNascimento><escolaridade>Superior</escolaridade></dados_deputado></deputado_><deputado_><id>2347</id><uri>https://dadosabertos.camara.leg.br/api/v2/deputados/2347</uri><nome>AUGUSTO DE LIMA</nome><siglaPartido/><uriPartido/><siglaUf>MG</siglaUf><idLegislatura>30</idLegislatura><urlFoto>http://www.camara.leg.br/internet/deputado/bandep/2347.jpg</urlFoto><dados_deputado><cpf/><nomeCivil>Antonio  Augusto de Lima</nomeCivil><sexo>M</sexo><urlWebsite/><redeSocial/><dataNascimento>1859-04-05</dataNascimento><dataFalecimento/><ufNascimento>MG</ufNascimento><municipioNascimento>Nova Lima</municipioNascimento><escolaridade/></dados_deputado></deputado_><deputado_><id>2360</id><uri>https://dadosabertos.camara.leg.br/api/v2/deputados/2360</uri><nome>AUGUSTO DO AMARAL</nome><siglaPartido/><uriPartido/><siglaUf>PE</siglaUf><idLegislatura>30</idLegislatura><urlFoto>http://www.camara.leg.br/internet/deputado/bandep/2360.jpg</urlFoto><dados_deputado/></deputado_><deputado_><id>130182</id><uri>https://dadosabertos.camara.leg.br/api/v2/deputados/130182</uri><nome>AUGUSTO PESTANA</nome><siglaPartido/><uriPartido/><siglaUf>RS</siglaUf><idLegislatura>30</idLegislatura><urlFoto>http://www.camara.leg.br/internet/deputado/bandep/130182.jpg</urlFoto><dados_deputado/></deputado_><deputado_><id>2405</id><uri>https://dadosabertos.camara.leg.br/api/v2/deputados/2405</uri><nome>AZURÉM FURTADO</nome><siglaPartido/><uriPartido/><siglaUf>DF</siglaUf><idLegislatura>30</idLegislatura><urlFoto>http://www.camara.leg.br/internet/deputado/bandep/2405.jpg</urlFoto><dados_deputado/></deputado_><deputado_><id>2361</id><uri>https://dadosabertos.camara.leg.br/api/v2/deputados/2361</uri><nome>BALTAZAR PEREIRA</nome><siglaPartido/><uriPartido/><siglaUf>PE</siglaUf><idLegislatura>30</idLegislatura><urlFoto>http://www.camara.leg.br/internet/deputado/bandep/2361.jpg</urlFoto><dados_deputado/></deputado_><deputado_><id>2439</id><uri>https://dadosabertos.camara.leg.br/api/v2/deputados/2439</uri><nome>BARBOSA GONÇALVES</nome><siglaPartido/><uriPartido/><siglaUf>RS</siglaUf><idLegislatura>30</idLegislatura><urlFoto>http://www.camara.leg.br/internet/deputado/bandep/2439.jpg</urlFoto><dados_deputado><cpf/><nomeCivil>José Barbosa Gonçalves</nomeCivil><sexo>M</sexo><urlWebsite/><redeSocial/><dataNascimento/><dataFalecimento/><ufNascimento/><municipioNascimento/><escolaridade/></dados_deputado></deputado_><deputado_><id>2423</id><uri>https://dadosabertos.camara.leg.br/api/v2/deputados/2423</uri><nome>BARBOSA RODRIGUES</nome><siglaPartido/><uriPartido/><siglaUf>PA</siglaUf><idLegislatura>30</idLegislatura><urlFoto>http://www.camara.leg.br/internet/deputado/bandep/2423.jpg</urlFoto><dados_deputado/></deputado_><deputado_><id>4272</id><uri>https://dadosabertos.camara.leg.br/api/v2/deputados/4272</uri><nome>BARROS PENTEADO</nome><siglaPartido/><uriPartido/><siglaUf>SP</siglaUf><idLegislatura>30</idLegislatura><urlFoto>http://www.camara.leg.br/internet/deputado/bandep/4272.jpg</urlFoto><dados_deputado/></deputado_><deputado_><id>130158</id><uri>https://dadosabertos.camara.leg.br/api/v2/deputados/130158</uri><nome>BENTO DE MIRANDA</nome><siglaPartido/><uriPartido/><siglaUf>PA</siglaUf><idLegislatura>30</idLegislatura><urlFoto>http://www.camara.leg.br/internet/deputado/bandep/130158.jpg</urlFoto><dados_deputado/></deputado_><deputado_><id>4280</id><uri>https://dadosabertos.camara.leg.br/api/v2/deputados/4280</uri><nome>BUENO BRANDÃO</nome><siglaPartido/><uriPartido/><siglaUf>MG</siglaUf><idLegislatura>30</idLegislatura><urlFoto>http://www.camara.leg.br/internet/deputado/bandep/4280.jpg</urlFoto><dados_deputado/></deputado_><deputado_><id>130271</id><uri>https://dadosabertos.camara.leg.br/api/v2/deputados/130271</uri><nome>BUENO BRANDÃO FILHO</nome><siglaPartido>PRM</siglaPartido><uriPartido>https://dadosabertos.camara.leg.br/api/v2/partidos/36821</uriPartido><siglaUf>MG</siglaUf><idLegislatura>30</idLegislatura><urlFoto>http://www.camara.leg.br/internet/deputado/bandep/130271.jpg</urlFoto><dados_deputado><cpf/><nomeCivil>Julio Bueno Brandão Filho</nomeCivil><sexo>M</sexo><urlWebsite/><redeSocial/><dataNascimento>1883-04-05</dataNascimento><dataFalecimento/><ufNascimento>MG</ufNascimento><municipioNascimento>Ouro Fino</municipioNascimento><escolaridade>Superior</escolaridade></dados_deputado></deputado_><deputado_><id>4111</id><uri>https://dadosabertos.camara.leg.br/api/v2/deputados/4111</uri><nome>BUENO DE ANDRADA</nome><siglaPartido/><uriPartido/><siglaUf>SP</siglaUf><idLegislatura>30</idLegislatura><urlFoto>http://www.camara.leg.br/internet/deputado/bandep/4111.jpg</urlFoto><dados_deputado/></deputado_><deputado_><id>2429</id><uri>https://dadosabertos.camara.leg.br/api/v2/deputados/2429</uri><nome>CALDAS FILHO</nome><siglaPartido/><uriPartido/><siglaUf>PE</siglaUf><idLegislatura>30</idLegislatura><urlFoto>http://www.camara.leg.br/internet/deputado/bandep/2429.jpg</urlFoto><dados_deputado/></deputado_><deputado_><id>2063</id><uri>https://dadosabertos.camara.leg.br/api/v2/deputados/2063</uri><nome>CAMILO DE HOLANDA</nome><siglaPartido/><uriPartido/><siglaUf>PB</siglaUf><idLegislatura>30</idLegislatura><urlFoto>http://www.camara.leg.br/internet/deputado/bandep/2063.jpg</urlFoto><dados_deputado/></deputado_><deputado_><id>2138</id><uri>https://dadosabertos.camara.leg.br/api/v2/deputados/2138</uri><nome>CAMILO PRATES</nome><siglaPartido/><uriPartido/><siglaUf>MG</siglaUf><idLegislatura>30</idLegislatura><urlFoto>http://www.camara.leg.br/internet/deputado/bandep/2138.jpg</urlFoto><dados_deputado/></deputado_><deputado_><id>4115</id><uri>https://dadosabertos.camara.leg.br/api/v2/deputados/4115</uri><nome>CÂNDIDO MOTA</nome><siglaPartido/><uriPartido/><siglaUf>SP</siglaUf><idLegislatura>30</idLegislatura><urlFoto>http://www.camara.leg.br/internet/deputado/bandep/4115.jpg</urlFoto><dados_deputado/></deputado_><deputado_><id>4509</id><uri>https://dadosabertos.camara.leg.br/api/v2/deputados/4509</uri><nome>CARDOSO DE ALMEIDA</nome><siglaPartido/><uriPartido/><siglaUf>SP</siglaUf><idLegislatura>30</idLegislatura><urlFoto>http://www.camara.leg.br/internet/deputado/bandep/4509.jpg</urlFoto><dados_deputado/></deputado_><deputado_><id>4249</id><uri>https://dadosabertos.camara.leg.br/api/v2/deputados/4249</uri><nome>CARLOS GARCIA</nome><siglaPartido/><uriPartido/><siglaUf>SP</siglaUf><idLegislatura>30</idLegislatura><urlFoto>http://www.camara.leg.br/internet/deputado/bandep/4249.jpg</urlFoto><dados_deputado/></deputado_><deputado_><id>2323</id><uri>https://dadosabertos.camara.leg.br/api/v2/deputados/2323</uri><nome>CARLOS LEITÃO</nome><siglaPartido/><uriPartido/><siglaUf>BA</siglaUf><idLegislatura>30</idLegislatura><urlFoto>http://www.camara.leg.br/internet/deputado/bandep/2323.jpg</urlFoto><dados_deputado/></deputado_><deputado_><id>2140</id><uri>https://dadosabertos.camara.leg.br/api/v2/deputados/2140</uri><nome>CARLOS PEIXOTO FILHO</nome><siglaPartido/><uriPartido/><siglaUf>MG</siglaUf><idLegislatura>30</idLegislatura><urlFoto>http://www.camara.leg.br/internet/deputado/bandep/2140.jpg</urlFoto><dados_deputado/></deputado_><deputado_><id>2424</id><uri>https://dadosabertos.camara.leg.br/api/v2/deputados/2424</uri><nome>CASTELO BRANCO</nome><siglaPartido/><uriPartido/><siglaUf>PA</siglaUf><idLegislatura>30</idLegislatura><urlFoto>http://www.camara.leg.br/internet/deputado/bandep/2424.jpg</urlFoto><dados_deputado><cpf/><nomeCivil>Heitor Castello Branco</nomeCivil><sexo>M</sexo><urlWebsite/><redeSocial/><dataNascimento>1877-03-18</dataNascimento><dataFalecimento/><ufNascimento>PI</ufNascimento><municipioNascimento>Teresina</municipioNascimento><escolaridade>Superior</escolaridade></dados_deputado></deputado_><deputado_><id>130145</id><uri>https://dadosabertos.camara.leg.br/api/v2/deputados/130145</uri><nome>CELSO BAYMA</nome><siglaPartido/><uriPartido/><siglaUf>SC</siglaUf><idLegislatura>30</idLegislatura><urlFoto>http://www.camara.leg.br/internet/deputado/bandep/130145.jpg</urlFoto><dados_deputado/></deputado_><deputado_><id>130185</id><uri>https://dadosabertos.camara.leg.br/api/v2/deputados/130185</uri><nome>CÉZAR VERGUEIRO</nome><siglaPartido/><uriPartido/><siglaUf>SP</siglaUf><idLegislatura>30</idLegislatura><urlFoto>http://www.camara.leg.br/internet/deputado/bandep/130185.jpg</urlFoto><dados_deputado/></deputado_><deputado_><id>1788</id><uri>https://dadosabertos.camara.leg.br/api/v2/deputados/1788</uri><nome>CINCINATO BRAGA</nome><siglaPartido/><uriPartido/><siglaUf>SP</siglaUf><idLegislatura>30</idLegislatura><urlFoto>http://www.camara.leg.br/internet/deputado/bandep/1788.jpg</urlFoto><dados_deputado><cpf/><nomeCivil>Cincinato  César da Silva Braga</nomeCivil><sexo>M</sexo><urlWebsite/><redeSocial/><dataNascimento>1864-07-07</dataNascimento><dataFalecimento/><ufNascimento>SP</ufNascimento><municipioNascimento>Piracicaba</municipioNascimento><escolaridade>Superior</escolaridade></dados_deputado></deputado_><deputado_><id>2281</id><uri>https://dadosabertos.camara.leg.br/api/v2/deputados/2281</uri><nome>COELHO NETO</nome><siglaPartido/><uriPartido/><siglaUf>MA</siglaUf><idLegislatura>30</idLegislatura><urlFoto>http://www.camara.leg.br/internet/deputado/bandep/2281.jpg</urlFoto><dados_deputado/></deputado_><deputado_><id>1789</id><uri>https://dadosabertos.camara.leg.br/api/v2/deputados/1789</uri><nome>COSTA JÚNIOR</nome><siglaPartido/><uriPartido/><siglaUf>SP</siglaUf><idLegislatura>30</idLegislatura><urlFoto>http://www.camara.leg.br/internet/deputado/bandep/1789.jpg</urlFoto><dados_deputado/></deputado_><deputado_><id>2214</id><uri>https://dadosabertos.camara.leg.br/api/v2/deputados/2214</uri><nome>COSTA MARQUES</nome><siglaPartido/><uriPartido/><siglaUf>MT</siglaUf><idLegislatura>30</idLegislatura><urlFoto>http://www.camara.leg.br/internet/deputado/bandep/2214.jpg</urlFoto><dados_deputado/></deputado_><deputado_><id>4433</id><uri>https://dadosabertos.camara.leg.br/api/v2/deputados/4433</uri><nome>COSTA REGO</nome><siglaPartido/><uriPartido/><siglaUf>AL</siglaUf><idLegislatura>30</idLegislatura><urlFoto>http://www.camara.leg.br/internet/deputado/bandep/4433.jpg</urlFoto><dados_deputado><cpf/><nomeCivil>Pedro da Costa Rego</nomeCivil><sexo>M</sexo><urlWebsite/><redeSocial/><dataNascimento>1889-03-12</dataNascimento><dataFalecimento/><ufNascimento>AL</ufNascimento><municipioNascimento>Pilar</municipioNascimento><escolaridade/></dados_deputado></deputado_><deputado_><id>2430</id><uri>https://dadosabertos.camara.leg.br/api/v2/deputados/2430</uri><nome>COSTA RIBEIRO</nome><siglaPartido/><uriPartido/><siglaUf>PE</siglaUf><idLegislatura>30</idLegislatura><urlFoto>http://www.camara.leg.br/internet/deputado/bandep/2430.jpg</urlFoto><dados_deputado/></deputado_><deputado_><id>4186</id><uri>https://dadosabertos.camara.leg.br/api/v2/deputados/4186</uri><nome>CRISTIANO BRASIL</nome><siglaPartido/><uriPartido/><siglaUf>MG</siglaUf><idLegislatura>30</idLegislatura><urlFoto>http://www.camara.leg.br/internet/deputado/bandep/4186.jpg</urlFoto><dados_deputado/></deputado_><deputado_><id>1872</id><uri>https://dadosabertos.camara.leg.br/api/v2/deputados/1872</uri><nome>CUNHA LIMA</nome><siglaPartido/><uriPartido/><siglaUf>PB</siglaUf><idLegislatura>30</idLegislatura><urlFoto>http://www.camara.leg.br/internet/deputado/bandep/1872.jpg</urlFoto><dados_deputado/></deputado_><deputado_><id>4261</id><uri>https://dadosabertos.camara.leg.br/api/v2/deputados/4261</uri><nome>CUNHA MACHADO</nome><siglaPartido/><uriPartido/><siglaUf>MA</siglaUf><idLegislatura>30</idLegislatura><urlFoto>http://www.camara.leg.br/internet/deputado/bandep/4261.jpg</urlFoto><dados_deputado/></deputado_><deputado_><id>2410</id><uri>https://dadosabertos.camara.leg.br/api/v2/deputados/2410</uri><nome>DIOCLÉCIO BORGES</nome><siglaPartido/><uriPartido/><siglaUf>ES</siglaUf><idLegislatura>30</idLegislatura><urlFoto>http://www.camara.leg.br/internet/deputado/bandep/2410.jpg</urlFoto><dados_deputado/></deputado_><deputado_><id>2415</id><uri>https://dadosabertos.camara.leg.br/api/v2/deputados/2415</uri><nome>DOMINGOS DE FIGUEIREDO</nome><siglaPartido/><uriPartido/><siglaUf>MG</siglaUf><idLegislatura>30</idLegislatura><urlFoto>http://www.camara.leg.br/internet/deputado/bandep/2415.jpg</urlFoto><dados_deputado/></deputado_><deputado_><id>2161</id><uri>https://dadosabertos.camara.leg.br/api/v2/deputados/2161</uri><nome>DOMINGOS MASCARENHAS</nome><siglaPartido/><uriPartido/><siglaUf>RS</siglaUf><idLegislatura>30</idLegislatura><urlFoto>http://www.camara.leg.br/internet/deputado/bandep/2161.jpg</urlFoto><dados_deputado/></deputado_><deputado_><id>2132</id><uri>https://dadosabertos.camara.leg.br/api/v2/deputados/2132</uri><nome>DUNSHEE DE ABRANCHES</nome><siglaPartido/><uriPartido/><siglaUf>MA</siglaUf><idLegislatura>30</idLegislatura><urlFoto>http://www.camara.leg.br/internet/deputado/bandep/2132.jpg</urlFoto><dados_deputado/></deputado_><deputado_><id>2204</id><uri>https://dadosabertos.camara.leg.br/api/v2/deputados/2204</uri><nome>EDUARDO SABÓIA</nome><siglaPartido/><uriPartido/><siglaUf>CE</siglaUf><idLegislatura>30</idLegislatura><urlFoto>http://www.camara.leg.br/internet/deputado/bandep/2204.jpg</urlFoto><dados_deputado/></deputado_><deputado_><id>4120</id><uri>https://dadosabertos.camara.leg.br/api/v2/deputados/4120</uri><nome>EDUARDO STUDART</nome><siglaPartido/><uriPartido/><siglaUf>CE</siglaUf><idLegislatura>30</idLegislatura><urlFoto>http://www.camara.leg.br/internet/deputado/bandep/4120.jpg</urlFoto><dados_deputado/></deputado_><deputado_><id>2397</id><uri>https://dadosabertos.camara.leg.br/api/v2/deputados/2397</uri><nome>EFIGÊNIO DE SALES</nome><siglaPartido/><uriPartido/><siglaUf>AM</siglaUf><idLegislatura>30</idLegislatura><urlFoto>http://www.camara.leg.br/internet/deputado/bandep/2397.jpg</urlFoto><dados_deputado/></deputado_><deputado_><id>4122</id><uri>https://dadosabertos.camara.leg.br/api/v2/deputados/4122</uri><nome>ELIAS MARTINS</nome><siglaPartido/><uriPartido/><siglaUf>PI</siglaUf><idLegislatura>30</idLegislatura><urlFoto>http://www.camara.leg.br/internet/deputado/bandep/4122.jpg</urlFoto><dados_deputado><cpf/><nomeCivil>Elias Firmino de Souza Martins</nomeCivil><sexo>M</sexo><urlWebsite/><redeSocial/><dataNascimento>1868-01-01</dataNascimento><dataFalecimento/><ufNascimento>PI</ufNascimento><municipioNascimento>Teresina</municipioNascimento><escolaridade>Superior</escolaridade></dados_deputado></deputado_><deputado_><id>1593</id><uri>https://dadosabertos.camara.leg.br/api/v2/deputados/1593</uri><nome>ELPÍDIO MESQUITA</nome><siglaPartido/><uriPartido/><siglaUf>BA</siglaUf><idLegislatura>30</idLegislatura><urlFoto>http://www.camara.leg.br/internet/deputado/bandep/1593.jpg</urlFoto><dados_deputado/></deputado_><deputado_><id>2218</id><uri>https://dadosabertos.camara.leg.br/api/v2/deputados/2218</uri><nome>EPAMINONDAS OTONI</nome><siglaPartido/><uriPartido/><siglaUf>MG</siglaUf><idLegislatura>30</idLegislatura><urlFoto>http://www.camara.leg.br/internet/deputado/bandep/2218.jpg</urlFoto><dados_deputado/></deputado_><deputado_><id>2451</id><uri>https://dadosabertos.camara.leg.br/api/v2/deputados/2451</uri><nome>ESPERIDIÃO MONTEIRO</nome><siglaPartido/><uriPartido/><siglaUf>SE</siglaUf><idLegislatura>30</idLegislatura><urlFoto>http://www.camara.leg.br/internet/deputado/bandep/2451.jpg</urlFoto><dados_deputado/></deputado_><deputado_><id>4256</id><uri>https://dadosabertos.camara.leg.br/api/v2/deputados/4256</uri><nome>ESTÁCIO COIMBRA</nome><siglaPartido/><uriPartido/><siglaUf>PE</siglaUf><idLegislatura>30</idLegislatura><urlFoto>http://www.camara.leg.br/internet/deputado/bandep/4256.jpg</urlFoto><dados_deputado/></deputado_><deputado_><id>2447</id><uri>https://dadosabertos.camara.leg.br/api/v2/deputados/2447</uri><nome>EUGÊNIO MÜLLER</nome><siglaPartido/><uriPartido/><siglaUf>SC</siglaUf><idLegislatura>30</idLegislatura><urlFoto>http://www.camara.leg.br/internet/deputado/bandep/2447.jpg</urlFoto><dados_deputado/></deputado_><deputado_><id>1949</id><uri>https://dadosabertos.camara.leg.br/api/v2/deputados/1949</uri><nome>EUGÊNIO TOURINHO</nome><siglaPartido/><uriPartido/><siglaUf>BA</siglaUf><idLegislatura>30</idLegislatura><urlFoto>http://www.camara.leg.br/internet/deputado/bandep/1949.jpg</urlFoto><dados_deputado/></deputado_><deputado_><id>2109</id><uri>https://dadosabertos.camara.leg.br/api/v2/deputados/2109</uri><nome>EUSÉBIO DE ANDRADE</nome><siglaPartido/><uriPartido/><siglaUf>AL</siglaUf><idLegislatura>30</idLegislatura><urlFoto>http://www.camara.leg.br/internet/deputado/bandep/2109.jpg</urlFoto><dados_deputado><cpf/><nomeCivil>Euzebio Francisco de Andrade</nomeCivil><sexo>M</sexo><urlWebsite/><redeSocial/><dataNascimento>1866-04-15</dataNascimento><dataFalecimento/><ufNascimento/><municipioNascimento/><escolaridade>Superior</escolaridade></dados_deputado></deputado_><deputado_><id>4259</id><uri>https://dadosabertos.camara.leg.br/api/v2/deputados/4259</uri><nome>EVARISTO DO AMARAL</nome><siglaPartido/><uriPartido/><siglaUf>RS</siglaUf><idLegislatura>30</idLegislatura><urlFoto>http://www.camara.leg.br/internet/deputado/bandep/4259.jpg</urlFoto><dados_deputado/></deputado_><deputado_><id>2431</id><uri>https://dadosabertos.camara.leg.br/api/v2/deputados/2431</uri><nome>FÁBIO DE BARROS</nome><siglaPartido/><uriPartido/><siglaUf>PE</siglaUf><idLegislatura>30</idLegislatura><urlFoto>http://www.camara.leg.br/internet/deputado/bandep/2431.jpg</urlFoto><dados_deputado/></deputado_><deputado_><id>4469</id><uri>https://dadosabertos.camara.leg.br/api/v2/deputados/4469</uri><nome>FARIA SOUTO</nome><siglaPartido/><uriPartido/><siglaUf>RJ</siglaUf><idLegislatura>30</idLegislatura><urlFoto>http://www.camara.leg.br/internet/deputado/bandep/4469.jpg</urlFoto><dados_deputado/></deputado_><deputado_><id>4192</id><uri>https://dadosabertos.camara.leg.br/api/v2/deputados/4192</uri><nome>FAUSTO FERRAZ</nome><siglaPartido/><uriPartido/><siglaUf>MG</siglaUf><idLegislatura>30</idLegislatura><urlFoto>http://www.camara.leg.br/internet/deputado/bandep/4192.jpg</urlFoto><dados_deputado/></deputado_><deputado_><id>1800</id><uri>https://dadosabertos.camara.leg.br/api/v2/deputados/1800</uri><nome>FELISBELO FREIRE</nome><siglaPartido/><uriPartido/><siglaUf>SE</siglaUf><idLegislatura>30</idLegislatura><urlFoto>http://www.camara.leg.br/internet/deputado/bandep/1800.jpg</urlFoto><dados_deputado><cpf/><nomeCivil>Felisbello Firmo de Oliveira Freire</nomeCivil><sexo>M</sexo><urlWebsite/><redeSocial/><dataNascimento>1858-01-30</dataNascimento><dataFalecimento/><ufNascimento>SE</ufNascimento><municipioNascimento/><escolaridade>Superior</escolaridade></dados_deputado></deputado_><deputado_><id>2443</id><uri>https://dadosabertos.camara.leg.br/api/v2/deputados/2443</uri><nome>FELIX DE MIRANDA</nome><siglaPartido/><uriPartido/><siglaUf>RJ</siglaUf><idLegislatura>30</idLegislatura><urlFoto>http://www.camara.leg.br/internet/deputado/bandep/2443.jpg</urlFoto><dados_deputado/></deputado_><deputado_><id>4209</id><uri>https://dadosabertos.camara.leg.br/api/v2/deputados/4209</uri><nome>FELIX PACHECO</nome><siglaPartido/><uriPartido/><siglaUf>PI</siglaUf><idLegislatura>30</idLegislatura><urlFoto>http://www.camara.leg.br/internet/deputado/bandep/4209.jpg</urlFoto><dados_deputado><cpf/><nomeCivil>José Felix Alves Pacheco</nomeCivil><sexo>M</sexo><urlWebsite/><redeSocial/><dataNascimento>1879-08-02</dataNascimento><dataFalecimento/><ufNascimento>PI</ufNascimento><municipioNascimento>Teresina</municipioNascimento><escolaridade/></dados_deputado></deputado_><deputado_><id>2183</id><uri>https://dadosabertos.camara.leg.br/api/v2/deputados/2183</uri><nome>FERREIRA BRAGA</nome><siglaPartido/><uriPartido/><siglaUf>SP</siglaUf><idLegislatura>30</idLegislatura><urlFoto>http://www.camara.leg.br/internet/deputado/bandep/2183.jpg</urlFoto><dados_deputado/></deputado_><deputado_><id>2406</id><uri>https://dadosabertos.camara.leg.br/api/v2/deputados/2406</uri><nome>FLÁVIO DA SILVEIRA</nome><siglaPartido/><uriPartido/><siglaUf>DF</siglaUf><idLegislatura>30</idLegislatura><urlFoto>http://www.camara.leg.br/internet/deputado/bandep/2406.jpg</urlFoto><dados_deputado/></deputado_><deputado_><id>2336</id><uri>https://dadosabertos.camara.leg.br/api/v2/deputados/2336</uri><nome>FLORIANO DE BRITO</nome><siglaPartido/><uriPartido/><siglaUf>DF</siglaUf><idLegislatura>30</idLegislatura><urlFoto>http://www.camara.leg.br/internet/deputado/bandep/2336.jpg</urlFoto><dados_deputado/></deputado_><deputado_><id>2388</id><uri>https://dadosabertos.camara.leg.br/api/v2/deputados/2388</uri><nome>FRANCISCO ALVES</nome><siglaPartido/><uriPartido/><siglaUf>SP</siglaUf><idLegislatura>30</idLegislatura><urlFoto>http://www.camara.leg.br/internet/deputado/bandep/2388.jpg</urlFoto><dados_deputado/></deputado_><deputado_><id>130142</id><uri>https://dadosabertos.camara.leg.br/api/v2/deputados/130142</uri><nome>FRANCISCO BRESSANE</nome><siglaPartido/><uriPartido/><siglaUf>MG</siglaUf><idLegislatura>30</idLegislatura><urlFoto>http://www.camara.leg.br/internet/deputado/bandep/130142.jpg</urlFoto><dados_deputado/></deputado_><deputado_><id>2349</id><uri>https://dadosabertos.camara.leg.br/api/v2/deputados/2349</uri><nome>FRANCISCO PAOLIELO</nome><siglaPartido/><uriPartido/><siglaUf>MG</siglaUf><idLegislatura>30</idLegislatura><urlFoto>http://www.camara.leg.br/internet/deputado/bandep/2349.jpg</urlFoto><dados_deputado/></deputado_><deputado_><id>1584</id><uri>https://dadosabertos.camara.leg.br/api/v2/deputados/1584</uri><nome>FREDERICO BORGES</nome><siglaPartido/><uriPartido/><siglaUf>CE</siglaUf><idLegislatura>30</idLegislatura><urlFoto>http://www.camara.leg.br/internet/deputado/bandep/1584.jpg</urlFoto><dados_deputado><cpf/><nomeCivil>Frederico Augusto Borges</nomeCivil><sexo>M</sexo><urlWebsite/><redeSocial/><dataNascimento>1853-04-07</dataNascimento><dataFalecimento/><ufNascimento>CE</ufNascimento><municipioNascimento>Fortaleza</municipioNascimento><escolaridade>Superior</escolaridade></dados_deputado></deputado_><deputado_><id>4132</id><uri>https://dadosabertos.camara.leg.br/api/v2/deputados/4132</uri><nome>FREDERICO LUNDGREEN</nome><siglaPartido/><uriPartido/><siglaUf>PE</siglaUf><idLegislatura>30</idLegislatura><urlFoto>http://www.camara.leg.br/internet/deputado/bandep/4132.jpg</urlFoto><dados_deputado/></deputado_><deputado_><id>4203</id><uri>https://dadosabertos.camara.leg.br/api/v2/deputados/4203</uri><nome>GALEÃO CARVALHAL</nome><siglaPartido/><uriPartido/><siglaUf>SP</siglaUf><idLegislatura>30</idLegislatura><urlFoto>http://www.camara.leg.br/internet/deputado/bandep/4203.jpg</urlFoto><dados_deputado><cpf/><nomeCivil>João Galeão Carvalhal</nomeCivil><sexo>M</sexo><urlWebsite/><redeSocial/><dataNascimento>1859-10-11</dataNascimento><dataFalecimento/><ufNascimento>BA</ufNascimento><municipioNascimento>Salvador</municipioNascimento><escolaridade>Superior</escolaridade></dados_deputado></deputado_><deputado_><id>2432</id><uri>https://dadosabertos.camara.leg.br/api/v2/deputados/2432</uri><nome>GERVASIO FIORAVANTE</nome><siglaPartido/><uriPartido/><siglaUf>PE</siglaUf><idLegislatura>30</idLegislatura><urlFoto>http://www.camara.leg.br/internet/deputado/bandep/2432.jpg</urlFoto><dados_deputado/></deputado_><deputado_><id>2452</id><uri>https://dadosabertos.camara.leg.br/api/v2/deputados/2452</uri><nome>GILBERTO AMADO</nome><siglaPartido/><uriPartido/><siglaUf>SE</siglaUf><idLegislatura>30</idLegislatura><urlFoto>http://www.camara.leg.br/internet/deputado/bandep/2452.jpg</urlFoto><dados_deputado/></deputado_></dados><links><link><rel>self</rel><href>https://dadosabertos.camara.leg.br/api/v2/deputados?idLegislatura=30&amp;itens=550</href></link><link><rel>next</rel><href>https://dadosabertos.camara.leg.br/api/v2/deputados/?idLegislatura=30&amp;pagina=2&amp;itens=100</href></link><link><rel>first</rel><href>https://dadosabertos.camara.leg.br/api/v2/deputados/?idLegislatura=30&amp;pagina=1&amp;itens=100</href></link><link><rel>last</rel><href>https://dadosabertos.camara.leg.br/api/v2/deputados/?idLegislatura=30&amp;pagina=3&amp;itens=100</href></link></links></xml>